usbx/__init__.py
usbx/configuration.py
usbx/controltransfer.py
usbx/device.py
usbx/enums.py
usbx/exceptions.py
usbx/py.typed
usbx/registry.py
usbx/usb.py
usbx/version.py
usbx/_common/confparser.py
usbx/_common/ctypesfunc.py
usbx/_common/devicebase.py
usbx/_common/registrybase.py
usbx/_linux/asynctransfer.py
usbx/_linux/ioctl.py
usbx/_linux/linuxdevice.py
usbx/_linux/linuxregistry.py
usbx/_linux/udev.py
usbx/_linux/usbdevfs.py
usbx/_macos/corefoundation.py
usbx/_macos/iokit.py
usbx/_macos/macosdevice.py
usbx/_macos/macoserrors.py
usbx/_macos/macosregistry.py
usbx/_macos/transfertimeout.py
usbx/_windows/deviceinfoset.py
usbx/_windows/kernel32.py
usbx/_windows/ole32.py
usbx/_windows/setupapi.py
usbx/_windows/user32.py
usbx/_windows/windevice.py
usbx/_windows/winerror.py
usbx/_windows/winregistry.py
usbx/_windows/winusb.py
usbx-0.8.3.dist-info/licenses/LICENSE
usbx-0.8.3.dist-info/METADATA
usbx-0.8.3.dist-info/WHEEL
usbx-0.8.3.dist-info/top_level.txt
usbx-0.8.3.dist-info/RECORD
