Metadata-Version: 2.4
Name: usbx
Version: 0.8.3
Summary: Modern and user-friendly library for working with USB devices
Author-email: "Manuel Bl." <manuel.bleichenbacher@gmail.com>
License-Expression: MIT
Project-URL: Homepage, https://github.com/manuelbl/usbx
Project-URL: Issues, https://github.com/manuelbl/usbx/issues
Keywords: usb,usb-host,usb-devices
Classifier: Programming Language :: Python :: 3
Classifier: Operating System :: OS Independent
Requires-Python: >=3.9
License-File: LICENSE
Dynamic: license-file
